govdex/__init__.py
govdex-0.1.1.dist-info/WHEEL
govdex-0.1.1.dist-info/METADATA
govdex-0.1.1.dist-info/RECORD
